ekca_service/plugins/otp/privacyidea/__about__.py
ekca_service/plugins/otp/privacyidea/__init__.py
ekca_service/plugins/otp/privacyidea/__pycache__/__about__.cpython-38.opt-1.pyc
ekca_service/plugins/otp/privacyidea/__pycache__/__init__.cpython-38.opt-1.pyc
ekca_plugin_privacyidea-0.1.0.dist-info/LICENSE
ekca_plugin_privacyidea-0.1.0.dist-info/METADATA
ekca_plugin_privacyidea-0.1.0.dist-info/WHEEL
ekca_plugin_privacyidea-0.1.0.dist-info/entry_points.txt
ekca_plugin_privacyidea-0.1.0.dist-info/top_level.txt
ekca_plugin_privacyidea-0.1.0.dist-info/RECORD
