Metadata-Version: 2.1
Name: ekca-plugin-privacyidea
Version: 0.1.0
Summary: EKCA service OTP plugin for privacyIDEA
Home-page: UNKNOWN
Author: Michael Stroeder
Author-email: michael@stroeder.com
Maintainer: Michael Stroeder
Maintainer-email: michael@stroeder.com
License: Apache-2.0
Keywords: PKI,SSH,SSH-CA,Certificate
Platform: UNKNOWN
Classifier: Development Status :: 5 - Production/Stable
Classifier: Intended Audience :: Information Technology
Classifier: Intended Audience :: System Administrators
Classifier: License :: OSI Approved :: Apache Software License
Classifier: Operating System :: OS Independent
Classifier: Programming Language :: Python
Classifier: Programming Language :: Python :: 3
Classifier: Programming Language :: Python :: 3.4
Classifier: Programming Language :: Python :: 3.5
Classifier: Programming Language :: Python :: 3.6
Classifier: Programming Language :: Python :: 3.7
Classifier: Programming Language :: Python :: 3.8
Classifier: Programming Language :: Python :: 3.9
Classifier: Programming Language :: Python :: 3 :: Only
Classifier: Topic :: System :: Systems Administration
Classifier: Topic :: System :: Systems Administration :: Authentication/Directory
Requires-Python: >=3.4.*
License-File: LICENSE
Requires-Dist: ekca-service (>=0.1.3)
Requires-Dist: requests (>=2.22)
Requires-Dist: responses (>=0.10)
Requires-Dist: setuptools
